pmdownloader/__init__.py
pmdownloader/pmdownloader.py
pmdownloader-1.0.1.dist-info/LICENSE
pmdownloader-1.0.1.dist-info/METADATA
pmdownloader-1.0.1.dist-info/WHEEL
pmdownloader-1.0.1.dist-info/top_level.txt
pmdownloader-1.0.1.dist-info/RECORD
