Metadata-Version: 2.1
Name: pmdownloader
Version: 1.0.1
Summary: Library to download media files
Home-page: https://github.com/razin-s/pmdownloader
Author: Razin Sami
Author-email: razinbrz69@gmail.com
License: UNKNOWN
Project-URL: Bug Tracker, https://github.com/razin-s/pmdownloader/issues
Keywords: media,video,audio,mp3,mp4,downloader
Platform: UNKNOWN
Classifier: Programming Language :: Python :: 3
Classifier: License :: OSI Approved :: MIT License
Classifier: Operating System :: OS Independent
Requires-Python: >=3.6
License-File: LICENSE
Requires-Dist: requests
